llm_tools_execute_shell.py
llm_tools_execute_shell-0.1.2.dist-info/licenses/LICENSE
llm_tools_execute_shell-0.1.2.dist-info/METADATA
llm_tools_execute_shell-0.1.2.dist-info/WHEEL
llm_tools_execute_shell-0.1.2.dist-info/entry_points.txt
llm_tools_execute_shell-0.1.2.dist-info/top_level.txt
llm_tools_execute_shell-0.1.2.dist-info/RECORD
