Metadata-Version: 2.4
Name: llm-tools-execute-shell
Version: 0.1.2
Summary: A tool plugin for LLM to enable executing shell commands on the user's system.
Author: Joey Thometz
License-Expression: Apache-2.0
Requires-Python: >=3.9
License-File: LICENSE
Requires-Dist: llm
Requires-Dist: click
Provides-Extra: test
Requires-Dist: pytest; extra == "test"
Requires-Dist: llm-echo>=0.3a1; extra == "test"
Dynamic: license-file
